Metadata-Version: 2.4
Name: cdef-epi-analysis-plugin-tobias-version6
Version: 0.1.0
Classifier: Development Status :: 4 - Beta
Classifier: Intended Audience :: Science/Research
Classifier: License :: OSI Approved :: MIT License
Classifier: Programming Language :: Python :: 3
Classifier: Programming Language :: Python :: 3.11
Classifier: Programming Language :: Python :: 3.12
Classifier: Programming Language :: Python :: 3.13
Classifier: Programming Language :: Rust
Classifier: Programming Language :: Python :: Implementation :: CPython
Classifier: Programming Language :: Python :: Implementation :: PyPy
Classifier: Topic :: Scientific/Engineering :: Medical Science Apps.
Classifier: Topic :: Scientific/Engineering :: Information Analysis
Classifier: Topic :: Software Development :: Libraries :: Python Modules
Requires-Dist: polars==1.31.*
Requires-Dist: pyarrow>=10.0.0
License-File: LICENSE
Summary: High-performance epidemiological analysis plugin with case-control matching and temporal data extraction capabilities
Keywords: epidemiology,case-control,matching,temporal,registry,polars,rust,scd
Author: Tobias Kragholm
License: MIT
Requires-Python: >=3.12
